devento/__init__.py
devento/async_client.py
devento/client.py
devento/exceptions.py
devento/models.py
devento/sse_utils.py
devento-0.1.6.dist-info/METADATA
devento-0.1.6.dist-info/WHEEL
devento-0.1.6.dist-info/licenses/LICENSE
devento-0.1.6.dist-info/RECORD
